{
    "key": "group_60c1b849f1621",
    "title": "Page Settings",
    "fields": [
        {
            "key": "field_60c1b950e035b",
            "label": "Header",
            "name": "",
            "type": "tab",
            "instructions": "",
            "required": 0,
            "conditional_logic": 0,
            "wrapper": {
                "width": "",
                "class": "",
                "id": ""
            },
            "placement": "left",
            "endpoint": 0
        },
        {
            "key": "field_60c1ba4476746",
            "label": "Header Style",
            "name": "ca_header_style",
            "type": "radio",
            "instructions": "",
            "required": 0,
            "conditional_logic": 0,
            "wrapper": {
                "width": "",
                "class": "",
                "id": ""
            },
            "choices": {
                "default": "Default",
                "trans-light": "Transparent Background & Light Text"
            },
            "allow_null": 0,
            "other_choice": 0,
            "default_value": "default",
            "layout": "horizontal",
            "return_format": "value",
            "save_other_choice": 0
        },
        {
            "key": "field_60db4ede00030",
            "label": "Disable Breadcrumb",
            "name": "ca_breadcrumb_disabled",
            "type": "true_false",
            "instructions": "",
            "required": 0,
            "conditional_logic": 0,
            "wrapper": {
                "width": "",
                "class": "",
                "id": ""
            },
            "message": "",
            "default_value": 0,
            "ui": 1,
            "ui_on_text": "",
            "ui_off_text": ""
        }
    ],
    "location": [
        [
            {
                "param": "post_type",
                "operator": "==",
                "value": "page"
            }
        ]
    ],
    "menu_order": 100,
    "position": "normal",
    "style": "default",
    "label_placement": "top",
    "instruction_placement": "label",
    "hide_on_screen": "",
    "active": true,
    "description": "",
    "acfe_display_title": "",
    "acfe_autosync": [
        "json"
    ],
    "acfe_form": 0,
    "acfe_meta": "",
    "acfe_note": "",
    "modified": 1624985352
}